alexa_siterank/__init__.py
alexa_siterank/siterank.py
alexa_siterank/utils.py
alexa_siterank/future/__init__.py
alexa_siterank/future/future.py
alexa_siterank/future/utils.py
alexa_siterank/otr/__init__.py
alexa_siterank/otr/otr.py
alexa_siterank/otr/otrutils.py
alexa_siterank-1.0.2.dist-info/LICENSE
alexa_siterank-1.0.2.dist-info/METADATA
alexa_siterank-1.0.2.dist-info/WHEEL
alexa_siterank-1.0.2.dist-info/top_level.txt
alexa_siterank-1.0.2.dist-info/RECORD
