Metadata-Version: 2.1
Name: alexa-siterank
Version: 1.0.2
Summary: Get siterank & other data from Alexa Web Information Service
Home-page: https://github.com/mytja/SiteRank-Alexa
Author: mytja
License: UNKNOWN
Platform: UNKNOWN
Classifier: Programming Language :: Python :: 3
Classifier: License :: OSI Approved :: MIT License
Classifier: Operating System :: OS Independent
Requires-Python: >=3
Requires-Dist: httpx
